MatheFormulas/__init__.py
MatheFormulas/mensuration.py
MatheFormulas-1.0.dist-info/LICENSE
MatheFormulas-1.0.dist-info/METADATA
MatheFormulas-1.0.dist-info/WHEEL
MatheFormulas-1.0.dist-info/top_level.txt
MatheFormulas-1.0.dist-info/RECORD
