Metadata-Version: 2.1
Name: MatheFormulas
Version: 1.0
Summary: Math mensuration formulas
Author: CoderMadhuresh
Author-email: madhureshgupta1234@gmail.com
Keywords: python,python3,math,formulas,mensuration,MatheFormulas,coder,Madhuresh
Classifier: Development Status :: 1 - Planning
Classifier: Intended Audience :: Developers
Classifier: Programming Language :: Python :: 3
Classifier: Operating System :: Unix
Classifier: Operating System :: MacOS :: MacOS X
Classifier: Operating System :: Microsoft :: Windows
License-File: LICENSE
